netbox_contract/__init__.py
netbox_contract/constants.py
netbox_contract/filtersets.py
netbox_contract/forms.py
netbox_contract/models.py
netbox_contract/navigation.py
netbox_contract/search.py
netbox_contract/tables.py
netbox_contract/template_content.py
netbox_contract/urls.py
netbox_contract/views.py
netbox_contract/api/__init__.py
netbox_contract/api/serializers.py
netbox_contract/api/urls.py
netbox_contract/api/views.py
netbox_contract/locale/en/LC_MESSAGES/django.mo
netbox_contract/locale/en/LC_MESSAGES/django.po
netbox_contract/locale/fr/LC_MESSAGES/django.mo
netbox_contract/locale/fr/LC_MESSAGES/django.po
netbox_contract/migrations/0001_initial.py
netbox_contract/migrations/0002_alter_contract_circuit_and_more.py
netbox_contract/migrations/0003_alter_contract_custom_field_data_and_more.py
netbox_contract/migrations/0004_contract_currency_invoice_currency.py
netbox_contract/migrations/0005_contract_accounting_dimensions_and_more.py
netbox_contract/migrations/0006_alter_contract_circuit.py
netbox_contract/migrations/0007_invoice_date.py
netbox_contract/migrations/0008_invoice_comments.py
netbox_contract/migrations/0009_contract_external_reference.py
netbox_contract/migrations/0010_invoice_contracts.py
netbox_contract/migrations/0011_auto_20230122_2112.py
netbox_contract/migrations/0012_remove_invoice_contract.py
netbox_contract/migrations/0013_contract_documents_invoice_documents.py
netbox_contract/migrations/0014_contract_end_date.py
netbox_contract/migrations/0015_contractassignement.py
netbox_contract/migrations/0016_contract_parent.py
netbox_contract/migrations/0017_alter_contract_accounting_dimensions.py
netbox_contract/migrations/0018_contract_external_partie_object_id_and_more.py
netbox_contract/migrations/0019_auto_20230924_1813.py
netbox_contract/migrations/0020_alter_contract_external_partie.py
netbox_contract/migrations/0021_alter_contract_external_partie.py
netbox_contract/migrations/0022_alter_contract_internal_partie_alter_contract_parent.py
netbox_contract-2.4.4.dist-info/licenses/LICENSE
netbox_contract-2.4.4.dist-info/METADATA
netbox_contract-2.4.4.dist-info/WHEEL
netbox_contract-2.4.4.dist-info/top_level.txt
netbox_contract-2.4.4.dist-info/RECORD
