Metadata-Version: 2.4
Name: netbox-contract
Version: 2.4.4
Summary: Contract management plugin for Netbox
Author-email: Marc Lebreuil <marc@famillelebreuil.net>
Project-URL: Homepage, https://github.com/mlebreuil/netbox-contract
Project-URL: Bug Tracker, https://github.com/mlebreuil/netbox-contract/issues
Classifier: Programming Language :: Python :: 3
Classifier: License :: OSI Approved :: MIT License
Classifier: Operating System :: OS Independent
Requires-Python: >=3.12
License-File: LICENSE
Requires-Dist: python-dateutil
Requires-Dist: drf_yasg
Requires-Dist: Django
Provides-Extra: dev
Requires-Dist: check-manifest; extra == "dev"
Requires-Dist: mkdocs; extra == "dev"
Requires-Dist: mkdocs-material; extra == "dev"
Requires-Dist: ruff; extra == "dev"
Provides-Extra: test
Requires-Dist: coverage; extra == "test"
Requires-Dist: pytest; extra == "test"
Requires-Dist: pytest-cov; extra == "test"
Dynamic: license-file
